pychoir/__init__.py
pychoir/__version__.py
pychoir/callables.py
pychoir/comparisons.py
pychoir/containers.py
pychoir/core.py
pychoir/existential.py
pychoir/integration.py
pychoir/logical.py
pychoir/numeric.py
pychoir/py.typed
pychoir/strings.py
pychoir/types.py
pychoir/utils.py
pychoir-0.0.29.dist-info/METADATA
pychoir-0.0.29.dist-info/WHEEL
pychoir-0.0.29.dist-info/licenses/LICENSE.txt
pychoir-0.0.29.dist-info/RECORD
