Metadata-Version: 2.4
Name: pychoir
Version: 0.0.29
Summary: Test Matchers for humans
Project-URL: source, https://github.com/kajaste/pychoir
Author-email: Antti Kajander <9019523+kajaste@users.noreply.github.com>
License: MIT License
License-File: LICENSE.txt
Keywords: error-handling,exception,matchers,mock,testing
Classifier: License :: OSI Approved :: MIT License
Classifier: Operating System :: OS Independent
Classifier: Programming Language :: Python :: 3
Classifier: Programming Language :: Python :: 3.6
Classifier: Programming Language :: Python :: 3.7
Classifier: Programming Language :: Python :: 3.8
Classifier: Programming Language :: Python :: 3.9
Classifier: Programming Language :: Python :: 3.10
Classifier: Programming Language :: Python :: 3.11
Classifier: Programming Language :: Python :: 3.12
Classifier: Programming Language :: Python :: 3.13
Classifier: Programming Language :: Python :: Implementation :: CPython
Classifier: Programming Language :: Python :: Implementation :: PyPy
Requires-Python: >=3.6
